chat_chain/__init__.py
chat_chain/chain.py
chat_chain/utils/__init__.py
chat_chain/utils/chat_prompt_template.py
chat_chain/utils/telemetry.py
chat_chain-0.1.0.dist-info/LICENSE
chat_chain-0.1.0.dist-info/METADATA
chat_chain-0.1.0.dist-info/WHEEL
chat_chain-0.1.0.dist-info/top_level.txt
chat_chain-0.1.0.dist-info/RECORD
